{"equipment":"5df7b9abef12bf7a252437a1","stash":"5df7b9abef12bf7a2524385f","questRaidItems":"5df7b9abef12bf7a25243860","questStashItems":"5df7b9abef12bf7a25243861","items":[{"_id":"5df7b9abef12bf7a252437a1","_tpl":"55d7217a4bdc2d86028b456d"},{"_id":"5df7b9abef12bf7a252437a0","_tpl":"557ffd194bdc2d28148b457f","parentId":"5df7b9abef12bf7a252437a1","slotId":"Pockets"},{"_id":"5df7b9abef12bf7a2524385f","_tpl":"5811ce772459770e9e5f9532"},{"_id":"5df7b9abef12bf7a25243861","_tpl":"5963866b86f7747bfa1c4462"},{"_id":"5df7b9abef12bf7a25243860","_tpl":"5963866286f7747bf429b572"},{"_id":"I75114505839001907IdT16b","_tpl":"5857a8bc2459772bad15db29","parentId":"5df7b9abef12bf7a252437a1","slotId":"SecuredContainer","upd":{"StackObjectsCount":1}},{"_id":"I7512351547607151113vcRN","_tpl":"5b3f16c486f7747c327f55f7","parentId":"5df7b9abef12bf7a252437a1","slotId":"ArmBand","upd":{"StackObjectsCount":1}},{"_id":"I751823243573346196Ph2Mu","_tpl":"58dd3ad986f77403051cba8f","parentId":"I75114505839001907IdT16b","slotId":"main","location":{"x":0,"y":0,"r":"Horizontal","isSearched":true},"upd":{"StackObjectsCount":40}},{"_id":"I75183144396526304931xF9","_tpl":"5d5d646386f7742797261fd9","parentId":"5df7b9abef12bf7a252437a1","slotId":"TacticalVest"},{"_id":"b7ce24baf9d58d4a5bef82d8","_tpl":"5ac6ru7build1665067263438","parentId":"I75183144396526304931xF9","slotId":"mod_equipment_000"},{"_id":"I751831524883518429zUDu4","_tpl":"5c1a1cc52e221602b3136e3d","parentId":"5df7b9abef12bf7a252437a1","slotId":"Eyewear","upd":{"StackObjectsCount":1}},{"_id":"I751831564521424153M48UB","_tpl":"5aa2ba19e5b5b00014028f4e","parentId":"5df7b9abef12bf7a252437a1","slotId":"Headwear","upd":{"StackObjectsCount":1}},{"_id":"I751832257058915405QjjRh","_tpl":"5c501a4d2e221602b412b540","parentId":"5df7b9abef12bf7a252437a1","slotId":"FirstPrimaryWeapon","upd":{"StackObjectsCount":1}},{"_id":"I75183221709906532ozo8bP","_tpl":"5c5039be2e221602b177c9ff","parentId":"I751832257058915405QjjRh","slotId":"mod_gas_block","upd":{"StackObjectsCount":1}},{"_id":"I75183224798646479w6m4yh","_tpl":"5c503d0a2e221602b542b7ef","parentId":"I751832257058915405QjjRh","slotId":"mod_reciever","upd":{"StackObjectsCount":1}},{"_id":"I75183227288198742DeXEmW","_tpl":"5c503af12e221602b177ca02","parentId":"I751832257058915405QjjRh","slotId":"mod_stock","upd":{"StackObjectsCount":1}},{"_id":"I751832111120216854Y0fb8","_tpl":"58dd3ad986f77403051cba8f","parentId":"I751832167410795938Ix7l9","slotId":"cartridges","location":0,"upd":{"StackObjectsCount":10}},{"_id":"I751832164636501354etUnp","_tpl":"5c503ad32e2216398b5aada2","parentId":"I751832257058915405QjjRh","slotId":"mod_magazine","upd":{"StackObjectsCount":1}},{"_id":"I751832163477853983h3gn6","_tpl":"5c503ad32e2216398b5aada2","parentId":"I75183144396526304931xF9","slotId":"7","location":{"x":0,"y":0,"r":"Horizontal","isSearched":true},"upd":{"StackObjectsCount":1}},{"_id":"I751832167410795938Ix7l9","_tpl":"5c503ad32e2216398b5aada2","parentId":"I75183144396526304931xF9","slotId":"1","location":{"x":0,"y":0,"r":"Horizontal","isSearched":true},"upd":{"StackObjectsCount":1}},{"_id":"I751832168413780482OaaWz","_tpl":"5c503ad32e2216398b5aada2","parentId":"I75183144396526304931xF9","slotId":"2","location":{"x":0,"y":0,"r":"Horizontal","isSearched":true},"upd":{"StackObjectsCount":1}},{"_id":"I751832179424851134tHREJ","_tpl":"5649d9a14bdc2d79388b4580","parentId":"I751832257058915405QjjRh","slotId":"mod_sight_rear","upd":{"StackObjectsCount":1}},{"_id":"I751832275916950167t1EPl","_tpl":"570fd721d2720bc5458b4596","parentId":"I751832179424851134tHREJ","slotId":"mod_scope","upd":{"StackObjectsCount":1}},{"_id":"I751832361273415664lEWML","_tpl":"58dd3ad986f77403051cba8f","parentId":"I751832164636501354etUnp","slotId":"cartridges","location":0,"upd":{"StackObjectsCount":10}},{"_id":"I751832473915476750JEy1r","_tpl":"58dd3ad986f77403051cba8f","parentId":"I751832168413780482OaaWz","slotId":"cartridges","location":0,"upd":{"StackObjectsCount":10}},{"_id":"I7518324877881749946oxt8","_tpl":"58dd3ad986f77403051cba8f","parentId":"I751832163477853983h3gn6","slotId":"cartridges","location":0,"upd":{"StackObjectsCount":10}},{"_id":"I75183304858826699s44MLC","_tpl":"5449016a4bdc2d6f028b456f","parentId":"5df7b9abef12bf7a252437a0","slotId":"pocket1","location":{"x":0,"y":0,"r":"Horizontal","isSearched":true},"upd":{"StackObjectsCount":1354}}],"fastPanel":{}}