{"equipment":"5feb6ce4b224b5479f420816","stash":"5feb6ce4b224b5479f420815","questRaidItems":"5feb6ce4b224b5479f420817","questStashItems":"5feb6ce4b224b5479f420818","items":[{"_id":"5feb6ce4b224b5479f420816","_tpl":"55d7217a4bdc2d86028b456d"},{"_id":"5feb6ce4b224b5479f42084e","_tpl":"59d6088586f774275f37482f","parentId":"5feb6ce4b224b5479f420816","slotId":"FirstPrimaryWeapon"},{"_id":"5feb6ce4b224b5479f42084f","_tpl":"59d64ec286f774171d1e0a42","parentId":"5feb6ce4b224b5479f42084e","slotId":"mod_gas_block"},{"_id":"5feb6ce4b224b5479f420850","_tpl":"59d64f2f86f77417193ef8b3","parentId":"5feb6ce4b224b5479f42084f","slotId":"mod_handguard"},{"_id":"5feb6ce4b224b5479f420852","_tpl":"59e62cc886f77440d40b52a1","parentId":"5feb6ce4b224b5479f42084e","slotId":"mod_pistol_grip"},{"_id":"5feb6ce4b224b5479f420853","_tpl":"59d6507c86f7741b846413a2","parentId":"5feb6ce4b224b5479f42084e","slotId":"mod_reciever"},{"_id":"5feb6ce4b224b5479f420854","_tpl":"59d650cf86f7741b846413a4","parentId":"5feb6ce4b224b5479f42084e","slotId":"mod_sight_rear"},{"_id":"5feb6ce4b224b5479f420855","_tpl":"59d6514b86f774171a068a08","parentId":"5feb6ce4b224b5479f42084e","slotId":"mod_stock"},{"_id":"5feb6ce4b224b5479f420857","_tpl":"5a9fbacda2750c00141e080f","parentId":"5feb6ce4b224b5479f42084e","slotId":"mod_muzzle"},{"_id":"5feb6ce4b224b5479f420858","_tpl":"59e5f5a486f7746c530b3ce2","parentId":"5feb6ce4b224b5479f42084e","slotId":"mod_magazine"},{"_id":"5feb6ce4b224b5479f420859","_tpl":"59e0d99486f7744a32234762","parentId":"5feb6ce4b224b5479f420858","slotId":"cartridges","upd":{"StackObjectsCount":40}},{"_id":"5feb6ce4b224b5479f42085a","_tpl":"557ffd194bdc2d28148b457f","parentId":"5feb6ce4b224b5479f420816","slotId":"Pockets"},{"_id":"5feb6ce4b224b5479f420864","_tpl":"5448be9a4bdc2dfd2f8b456a","parentId":"5feb6ce4b224b5479f42085a","slotId":"pocket1","location":{"x":0,"y":0,"r":0}},{"_id":"5feb6ce4b224b5479f420865","_tpl":"5448be9a4bdc2dfd2f8b456a","parentId":"5feb6ce4b224b5479f42085a","slotId":"pocket2","location":{"x":0,"y":0,"r":0}},{"_id":"5feb6ce4b224b5479f42085b","_tpl":"5ca20abf86f77418567a43f2","parentId":"5feb6ce4b224b5479f420816","slotId":"TacticalVest"},{"_id":"5feb6ce4b224b5479f42085c","_tpl":"572b7fa524597762b747ce82","parentId":"5feb6ce4b224b5479f420816","slotId":"FaceCover"},{"_id":"5feb6ce4b224b5479f42085d","_tpl":"5f5f41476bdad616ad46d631","parentId":"5feb6ce4b224b5479f420816","slotId":"ArmorVest"},{"_id":"643d990bd3d8f8b0ed5ecb20","_tpl":"5ac6ru7build9022795232087","parentId":"5feb6ce4b224b5479f42085d","slotId":"mod_equipment_000"},{"_id":"5feb6ce4b224b5479f42085e","_tpl":"5bffdc370db834001d23eca8","parentId":"5feb6ce4b224b5479f420816","slotId":"Scabbard"},{"_id":"5feb6ce4b224b5479f42085f","_tpl":"5c0a794586f77461c458f892","parentId":"5feb6ce4b224b5479f420816","slotId":"SecuredContainer"},{"_id":"5feb6ce4b224b5479f420866","_tpl":"59e0d99486f7744a32234762","parentId":"5feb6ce4b224b5479f42085f","slotId":"main","location":{"x":0,"y":0,"r":0},"upd":{"StackObjectsCount":60}},{"_id":"5feb6ce4b224b5479f420867","_tpl":"59e0d99486f7744a32234762","parentId":"5feb6ce4b224b5479f42085f","slotId":"main","location":{"x":1,"y":0,"r":0},"upd":{"StackObjectsCount":60}},{"_id":"5feb6ce4b224b5479f420868","_tpl":"59e0d99486f7744a32234762","parentId":"5feb6ce4b224b5479f42085f","slotId":"main","location":{"x":2,"y":0,"r":0},"upd":{"StackObjectsCount":60}},{"_id":"5feb6ce4b224b5479f420869","_tpl":"59e0d99486f7744a32234762","parentId":"5feb6ce4b224b5479f42085f","slotId":"main","location":{"x":3,"y":0,"r":0},"upd":{"StackObjectsCount":60}},{"_id":"5feb6ce4b224b5479f42086a","_tpl":"59e0d99486f7744a32234762","parentId":"5feb6ce4b224b5479f42085f","slotId":"main","location":{"x":0,"y":1,"r":0},"upd":{"StackObjectsCount":60}},{"_id":"5feb6ce4b224b5479f42086b","_tpl":"59e0d99486f7744a32234762","parentId":"5feb6ce4b224b5479f42085f","slotId":"main","location":{"x":1,"y":1,"r":0},"upd":{"StackObjectsCount":60}},{"_id":"5feb6ce4b224b5479f42086c","_tpl":"59e0d99486f7744a32234762","parentId":"5feb6ce4b224b5479f42085f","slotId":"main","location":{"x":2,"y":1,"r":0},"upd":{"StackObjectsCount":60}},{"_id":"5feb6ce4b224b5479f42086d","_tpl":"59e0d99486f7744a32234762","parentId":"5feb6ce4b224b5479f42085f","slotId":"main","location":{"x":3,"y":1,"r":0},"upd":{"StackObjectsCount":60}},{"_id":"5feb6ce4b224b5479f42086e","_tpl":"59e0d99486f7744a32234762","parentId":"5feb6ce4b224b5479f42085f","slotId":"main","location":{"x":0,"y":2,"r":0},"upd":{"StackObjectsCount":60}},{"_id":"5feb6ce4b224b5479f42086f","_tpl":"59e0d99486f7744a32234762","parentId":"5feb6ce4b224b5479f42085f","slotId":"main","location":{"x":1,"y":2,"r":0},"upd":{"StackObjectsCount":60}},{"_id":"5feb6ce4b224b5479f420870","_tpl":"59e0d99486f7744a32234762","parentId":"5feb6ce4b224b5479f42085f","slotId":"main","location":{"x":2,"y":2,"r":0},"upd":{"StackObjectsCount":60}},{"_id":"5feb6ce4b224b5479f420871","_tpl":"59e0d99486f7744a32234762","parentId":"5feb6ce4b224b5479f42085f","slotId":"main","location":{"x":3,"y":2,"r":0},"upd":{"StackObjectsCount":60}},{"_id":"5feb6ce4b224b5479f420872","_tpl":"59e0d99486f7744a32234762","parentId":"5feb6ce4b224b5479f42085f","slotId":"main","location":{"x":0,"y":3,"r":0},"upd":{"StackObjectsCount":60}},{"_id":"5feb6ce4b224b5479f420873","_tpl":"59e0d99486f7744a32234762","parentId":"5feb6ce4b224b5479f42085f","slotId":"main","location":{"x":1,"y":3,"r":0},"upd":{"StackObjectsCount":60}},{"_id":"5feb6ce4b224b5479f420874","_tpl":"59e0d99486f7744a32234762","parentId":"5feb6ce4b224b5479f42085f","slotId":"main","location":{"x":2,"y":3,"r":0},"upd":{"StackObjectsCount":60}},{"_id":"5feb6ce4b224b5479f420875","_tpl":"59e0d99486f7744a32234762","parentId":"5feb6ce4b224b5479f42085f","slotId":"main","location":{"x":3,"y":3,"r":0},"upd":{"StackObjectsCount":60}},{"_id":"5feb6ce4b224b5479f420876","_tpl":"59e0d99486f7744a32234762","parentId":"5feb6ce4b224b5479f42085f","slotId":"main","location":{"x":0,"y":4,"r":0},"upd":{"StackObjectsCount":60}},{"_id":"5feb6ce4b224b5479f420877","_tpl":"59e0d99486f7744a32234762","parentId":"5feb6ce4b224b5479f42085f","slotId":"main","location":{"x":1,"y":4,"r":0},"upd":{"StackObjectsCount":60}},{"_id":"5feb6ce4b224b5479f420878","_tpl":"59e0d99486f7744a32234762","parentId":"5feb6ce4b224b5479f42085f","slotId":"main","location":{"x":2,"y":4,"r":0},"upd":{"StackObjectsCount":60}},{"_id":"5feb6ce4b224b5479f420879","_tpl":"59e0d99486f7744a32234762","parentId":"5feb6ce4b224b5479f42085f","slotId":"main","location":{"x":3,"y":4,"r":0},"upd":{"StackObjectsCount":60}},{"_id":"5feb6ce4b224b5479f42087a","_tpl":"59e0d99486f7744a32234762","parentId":"5feb6ce4b224b5479f42085f","slotId":"main","location":{"x":0,"y":5,"r":0},"upd":{"StackObjectsCount":60}},{"_id":"5feb6ce4b224b5479f42087b","_tpl":"59e0d99486f7744a32234762","parentId":"5feb6ce4b224b5479f42085f","slotId":"main","location":{"x":1,"y":5,"r":0},"upd":{"StackObjectsCount":60}},{"_id":"5feb6ce4b224b5479f42087c","_tpl":"59e0d99486f7744a32234762","parentId":"5feb6ce4b224b5479f42085f","slotId":"main","location":{"x":2,"y":5,"r":0},"upd":{"StackObjectsCount":60}},{"_id":"5feb6ce4b224b5479f42087d","_tpl":"59e0d99486f7744a32234762","parentId":"5feb6ce4b224b5479f42085f","slotId":"main","location":{"x":3,"y":5,"r":0},"upd":{"StackObjectsCount":60}},{"_id":"5feb6ce4b224b5479f42087e","_tpl":"59e0d99486f7744a32234762","parentId":"5feb6ce4b224b5479f42085f","slotId":"main","location":{"x":0,"y":6,"r":0},"upd":{"StackObjectsCount":60}},{"_id":"5feb6ce4b224b5479f42087f","_tpl":"59e0d99486f7744a32234762","parentId":"5feb6ce4b224b5479f42085f","slotId":"main","location":{"x":1,"y":6,"r":0},"upd":{"StackObjectsCount":60}},{"_id":"5feb6ce4b224b5479f420880","_tpl":"59e0d99486f7744a32234762","parentId":"5feb6ce4b224b5479f42085f","slotId":"main","location":{"x":2,"y":6,"r":0},"upd":{"StackObjectsCount":60}},{"_id":"5feb6ce4b224b5479f420881","_tpl":"59e0d99486f7744a32234762","parentId":"5feb6ce4b224b5479f42085f","slotId":"main","location":{"x":3,"y":6,"r":0},"upd":{"StackObjectsCount":60}},{"_id":"5feb6ce4b224b5479f420882","_tpl":"59e0d99486f7744a32234762","parentId":"5feb6ce4b224b5479f42085f","slotId":"main","location":{"x":0,"y":7,"r":0},"upd":{"StackObjectsCount":60}},{"_id":"5feb6ce4b224b5479f420883","_tpl":"59e0d99486f7744a32234762","parentId":"5feb6ce4b224b5479f42085f","slotId":"main","location":{"x":1,"y":7,"r":0},"upd":{"StackObjectsCount":60}},{"_id":"5feb6ce4b224b5479f420815","_tpl":"566abbc34bdc2d92178b4576"},{"_id":"5feb6ce4b224b5479f420818","_tpl":"5963866b86f7747bfa1c4462"},{"_id":"5feb6ce4b224b5479f420817","_tpl":"5963866286f7747bf429b572"}],"fastPanel":{}}