{"equipment":"5fe49444ae6628187a2e77b8","stash":"5fe49444ae6628187a2e78b8","questRaidItems":"5fe49444ae6628187a2e78b9","questStashItems":"5fe49444ae6628187a2e78ba","items":[{"_id":"5fe49444ae6628187a2e77b8","_tpl":"55d7217a4bdc2d86028b456d"},{"_id":"5fe49444ae6628187a2e77ac","_tpl":"5857a8bc2459772bad15db29","parentId":"5fe49444ae6628187a2e77b8","slotId":"SecuredContainer"},{"_id":"5fe49444ae6628187a2e77b6","_tpl":"557ffd194bdc2d28148b457f","parentId":"5fe49444ae6628187a2e77b8","slotId":"Pockets"},{"_id":"5fe49444ae6628187a2e78b8","_tpl":"5811ce772459770e9e5f9532"},{"_id":"5fe49444ae6628187a2e78ba","_tpl":"5963866b86f7747bfa1c4462"},{"_id":"5fe49444ae6628187a2e78b9","_tpl":"5963866286f7747bf429b572"},{"_id":"ec67d35ec3a54126afd2cc01","_tpl":"5755356824597772cb798962","parentId":"5fe49444ae6628187a2e77ac","slotId":"main","location":{"x":0,"y":1,"r":"Horizontal","isSearched":true},"upd":{"StackObjectsCount":1}},{"_id":"5f34dcfb48a3e80e30239f11","_tpl":"5c0fa877d174af02a012e1cf","parentId":"5fe49444ae6628187a2e77ac","slotId":"main","location":{"x":2,"y":1,"r":"Horizontal","isSearched":true},"upd":{"StackObjectsCount":1}},{"_id":"64969dbce072e5d85eed334b","_tpl":"5737201124597760fc4431f1","parentId":"5fe49444ae6628187a2e77ac","slotId":"main","location":{"x":2,"y":0,"r":"Horizontal","isSearched":true},"upd":{"StackObjectsCount":50}},{"_id":"803b29fe738e412c2def198a","_tpl":"5737201124597760fc4431f1","parentId":"5fe49444ae6628187a2e77ac","slotId":"main","location":{"x":1,"y":0,"r":"Horizontal","isSearched":true},"upd":{"StackObjectsCount":50}},{"_id":"db0d34c45eef97a1c97c9e60","_tpl":"5737201124597760fc4431f1","parentId":"5fe49444ae6628187a2e77ac","slotId":"main","location":{"x":0,"y":0,"r":"Horizontal","isSearched":true},"upd":{"StackObjectsCount":50}},{"_id":"9dcd489d84ea6d27f5efad64","_tpl":"572b7adb24597762ae139821","parentId":"5fe49444ae6628187a2e77b8","slotId":"TacticalVest","upd":{"StackObjectsCount":1}},{"_id":"8580509d19260ac61aa24b07","_tpl":"5b43271c5acfc432ff4dce65","parentId":"5fe49444ae6628187a2e77b8","slotId":"Headwear","upd":{"StackObjectsCount":1}},{"_id":"9457a70dcffbc662c6eff728","_tpl":"572b7fa524597762b747ce82","parentId":"5fe49444ae6628187a2e77b8","slotId":"FaceCover","upd":{"StackObjectsCount":1}},{"_id":"787c51517ee108ff1736e5ce","_tpl":"5c0d32fcd174af02a1659c75","parentId":"5fe49444ae6628187a2e77b8","slotId":"Eyewear","upd":{"StackObjectsCount":1}},{"_id":"362381d76b9f2fe168788184","_tpl":"544a5cde4bdc2d39388b456b","parentId":"5fe49444ae6628187a2e77b8","slotId":"Backpack","upd":{"StackObjectsCount":1}},{"_id":"d52b614855f88309fb0b6163","_tpl":"56e0598dd2720bb5668b45a6","parentId":"5fe49444ae6628187a2e77b8","slotId":"Holster","upd":{"Repairable":{"Durability":61,"MaxDurability":66}}},{"_id":"90eeddd007e3f9b6cf5c8bcd","_tpl":"5448c12b4bdc2d02308b456f","parentId":"9dcd489d84ea6d27f5efad64","slotId":"1","upd":{"StackObjectsCount":1},"location":{"x":0,"y":0,"r":"Horizontal","isSearched":true}},{"_id":"0939b8678b16d9718f24e5b9","_tpl":"56e05b06d2720bb2668b4586","parentId":"d52b614855f88309fb0b6163","slotId":"mod_muzzle","upd":{"StackObjectsCount":1}},{"_id":"509302770a7100fb33d2d035","_tpl":"56e05a6ed2720bd0748b4567","parentId":"d52b614855f88309fb0b6163","slotId":"mod_pistol_grip","upd":{"StackObjectsCount":1}},{"_id":"94311f1891392b1dae04434e","_tpl":"5737201124597760fc4431f1","parentId":"90eeddd007e3f9b6cf5c8bcd","slotId":"cartridges","location":0,"upd":{"StackObjectsCount":8}},{"_id":"84be416de3c71c2cdee3e245","_tpl":"5448c12b4bdc2d02308b456f","parentId":"d52b614855f88309fb0b6163","slotId":"mod_magazine","upd":{"StackObjectsCount":1}},{"_id":"adc2340faf4e64c98eff2de0","_tpl":"5448c12b4bdc2d02308b456f","parentId":"9dcd489d84ea6d27f5efad64","slotId":"4","location":{"x":0,"y":0,"r":"Horizontal","isSearched":true},"upd":{"StackObjectsCount":1}},{"_id":"50b0bf9af9234ea7c72a7b5f","_tpl":"5737201124597760fc4431f1","parentId":"84be416de3c71c2cdee3e245","slotId":"cartridges","location":0,"upd":{"StackObjectsCount":8}},{"_id":"1997a7ce922f0242656b9ceb","_tpl":"5737201124597760fc4431f1","parentId":"adc2340faf4e64c98eff2de0","slotId":"cartridges","location":0,"upd":{"StackObjectsCount":8}},{"_id":"d1df1692ac05e58d63101518","_tpl":"59e89d0986f77427600d226e","parentId":"362381d76b9f2fe168788184","slotId":"main","location":{"x":0,"y":0,"r":"Horizontal","isSearched":true},"upd":{"StackObjectsCount":1}},{"_id":"2f6c3b3d51ea836c5c45d332","_tpl":"5cbdaf89ae9215000e5b9c94","parentId":"9dcd489d84ea6d27f5efad64","slotId":"3","location":{"x":0,"y":0,"r":"Horizontal","isSearched":true},"upd":{"StackObjectsCount":1}},{"_id":"3855d5e42bf52f690554ddcf","_tpl":"5a9d6d21a2750c00137fa649","parentId":"362381d76b9f2fe168788184","slotId":"main","location":{"x":2,"y":0,"r":"Horizontal","isSearched":true},"upd":{"StackObjectsCount":1}}],"fastPanel":{}}