{"equipment":"5fe49444ae6628187a2e77b8","stash":"5fe49444ae6628187a2e78b8","questRaidItems":"5fe49444ae6628187a2e78b9","questStashItems":"5fe49444ae6628187a2e78ba","items":[{"_id":"5fe49444ae6628187a2e77b8","_tpl":"55d7217a4bdc2d86028b456d"},{"_id":"5fe49444ae6628187a2e77ac","_tpl":"5857a8bc2459772bad15db29","parentId":"5fe49444ae6628187a2e77b8","slotId":"SecuredContainer"},{"_id":"5fe49444ae6628187a2e77b6","_tpl":"557ffd194bdc2d28148b457f","parentId":"5fe49444ae6628187a2e77b8","slotId":"Pockets"},{"_id":"5fe49444ae6628187a2e78b8","_tpl":"5811ce772459770e9e5f9532"},{"_id":"5fe49444ae6628187a2e78ba","_tpl":"5963866b86f7747bfa1c4462"},{"_id":"5fe49444ae6628187a2e78b9","_tpl":"5963866286f7747bf429b572"},{"_id":"87d6ad37f10dbd6a20b25d7d","_tpl":"5e8f3423fd7471236e6e3b64","parentId":"5fe49444ae6628187a2e77ac","slotId":"main","location":{"x":2,"y":1,"r":"Horizontal","isSearched":true},"upd":{"StackObjectsCount":1}},{"_id":"7a8f974178c5509b271587da","_tpl":"590c657e86f77412b013051d","parentId":"5fe49444ae6628187a2e77ac","slotId":"main","location":{"x":0,"y":1,"r":"Horizontal","isSearched":true},"upd":{"StackObjectsCount":1}},{"_id":"b58b6cd054cde6b71e70fc12","_tpl":"5887431f2459777e1612938f","parentId":"5fe49444ae6628187a2e77ac","slotId":"main","location":{"x":1,"y":0,"r":"Horizontal","isSearched":true},"upd":{"StackObjectsCount":40}},{"_id":"cd37dd727d68c47cbef5f8de","_tpl":"5887431f2459777e1612938f","parentId":"5fe49444ae6628187a2e77ac","slotId":"main","location":{"x":0,"y":0,"r":"Horizontal","isSearched":true},"upd":{"StackObjectsCount":40}},{"_id":"7577d6c0cedf7e48fdceeb8e","_tpl":"5887431f2459777e1612938f","parentId":"5fe49444ae6628187a2e77ac","slotId":"main","location":{"x":2,"y":0,"r":"Horizontal","isSearched":true},"upd":{"StackObjectsCount":40}},{"_id":"a5b4e0d8d9def54c043be287","_tpl":"5ae08f0a5acfc408fb1398a1","parentId":"5fe49444ae6628187a2e77b8","slotId":"FirstPrimaryWeapon","upd":{"Repairable":{"Durability":61,"MaxDurability":66}}},{"_id":"a41a3d8aee3915e0b8903b10","_tpl":"5ae0973a5acfc4001562206c","parentId":"a5b4e0d8d9def54c043be287","slotId":"mod_magazine","upd":{"StackObjectsCount":1}},{"_id":"a581cc7ec5e738a217204c67","_tpl":"5ae096d95acfc400185c2c81","parentId":"a5b4e0d8d9def54c043be287","slotId":"mod_stock","upd":{"StackObjectsCount":1}},{"_id":"c327249af500bb9aaf2ca553","_tpl":"5ae09bff5acfc4001562219d","parentId":"a5b4e0d8d9def54c043be287","slotId":"mod_barrel","upd":{"StackObjectsCount":1}},{"_id":"37ed40a8affaef9889d62d4e","_tpl":"5ae099875acfc4001714e593","parentId":"c327249af500bb9aaf2ca553","slotId":"mod_sight_front","upd":{"StackObjectsCount":1}},{"_id":"456be4f0166c23016ce7ad89","_tpl":"5ae099925acfc4001a5fc7b3","parentId":"c327249af500bb9aaf2ca553","slotId":"mod_sight_rear","upd":{"StackObjectsCount":1}},{"_id":"86ac1bea3b137f826cdb9b00","_tpl":"59e7643b86f7742cbf2c109a","parentId":"5fe49444ae6628187a2e77b8","slotId":"TacticalVest","upd":{"StackObjectsCount":1}},{"_id":"cfefa27cd0d8ab80abcd65f5","_tpl":"5aa2ba46e5b5b000137b758d","parentId":"5fe49444ae6628187a2e77b8","slotId":"Headwear","upd":{"StackObjectsCount":1}},{"_id":"265fd8686c95ac2a06810ada","_tpl":"57e26fc7245977162a14b800","parentId":"5fe49444ae6628187a2e77b8","slotId":"Scabbard","upd":{"StackObjectsCount":1}},{"_id":"bc1a468a20b002c8d704a2c0","_tpl":"571a12c42459771f627b58a0","parentId":"5fe49444ae6628187a2e77b8","slotId":"Holster","upd":{"Repairable":{"Durability":61,"MaxDurability":66}}},{"_id":"6d3cad6d2b82078661b4c522","_tpl":"571a26d524597720680fbe8a","parentId":"bc1a468a20b002c8d704a2c0","slotId":"mod_barrel","upd":{"StackObjectsCount":1}},{"_id":"9c3bd828678dff9fe86e6adb","_tpl":"571a29dc2459771fb2755a6a","parentId":"bc1a468a20b002c8d704a2c0","slotId":"mod_magazine","upd":{"StackObjectsCount":1}},{"_id":"8dfe39aed1bb5093c25a06ed","_tpl":"5bffcf7a0db83400232fea79","parentId":"bc1a468a20b002c8d704a2c0","slotId":"mod_pistol_grip","upd":{"StackObjectsCount":1}},{"_id":"6d8efaba0d704ee046fb30b0","_tpl":"573603562459776430731618","parentId":"9c3bd828678dff9fe86e6adb","slotId":"cartridges","location":0,"upd":{"StackObjectsCount":8}},{"_id":"877e1ca51842d7d1b6e171b3","_tpl":"5887431f2459777e1612938f","parentId":"86ac1bea3b137f826cdb9b00","slotId":"4","location":{"x":0,"y":0,"r":"Horizontal","isSearched":true},"upd":{"StackObjectsCount":9}},{"_id":"8e4c36f8c84e508d77acc441","_tpl":"5b86a0e586f7745b600ccb23","parentId":"c327249af500bb9aaf2ca553","slotId":"mod_muzzle","upd":{"StackObjectsCount":1}},{"_id":"f4fca3077f546845eef1be0c","_tpl":"5887431f2459777e1612938f","parentId":"a41a3d8aee3915e0b8903b10","slotId":"cartridges","location":0,"upd":{"StackObjectsCount":5}},{"_id":"8a802b0e9bcad467eb605685","_tpl":"5887431f2459777e1612938f","parentId":"86ac1bea3b137f826cdb9b00","slotId":"5","location":{"x":0,"y":0,"r":"Horizontal","isSearched":true},"upd":{"StackObjectsCount":19}}],"fastPanel":{}}