{"equipment":"5fe49444ae6628187a2e77b8","stash":"5fe49444ae6628187a2e78b8","questRaidItems":"5fe49444ae6628187a2e78b9","questStashItems":"5fe49444ae6628187a2e78ba","items":[{"_id":"5fe49444ae6628187a2e77b8","_tpl":"55d7217a4bdc2d86028b456d"},{"_id":"5fe49444ae6628187a2e77ac","_tpl":"5857a8bc2459772bad15db29","parentId":"5fe49444ae6628187a2e77b8","slotId":"SecuredContainer"},{"_id":"5fe49444ae6628187a2e77b6","_tpl":"557ffd194bdc2d28148b457f","parentId":"5fe49444ae6628187a2e77b8","slotId":"Pockets"},{"_id":"5fe49444ae6628187a2e78b8","_tpl":"5811ce772459770e9e5f9532"},{"_id":"5fe49444ae6628187a2e78ba","_tpl":"5963866b86f7747bfa1c4462"},{"_id":"5fe49444ae6628187a2e78b9","_tpl":"5963866286f7747bf429b572"},{"_id":"b1eca0d9f2339d95211914dd","_tpl":"590c661e86f7741e566b646a","parentId":"5fe49444ae6628187a2e77ac","slotId":"main","location":{"x":0,"y":1,"r":"Vertical","isSearched":true},"upd":{"StackObjectsCount":1}},{"_id":"87d6ad37f10dbd6a20b25d7d","_tpl":"5e8f3423fd7471236e6e3b64","parentId":"5fe49444ae6628187a2e77ac","slotId":"main","location":{"x":1,"y":1,"r":"Horizontal","isSearched":true},"upd":{"StackObjectsCount":1}},{"_id":"c802f912cff8a1d8e35a6e2f","_tpl":"58dd3ad986f77403051cba8f","parentId":"5fe49444ae6628187a2e77ac","slotId":"main","location":{"x":1,"y":0,"r":"Horizontal","isSearched":true},"upd":{"StackObjectsCount":40}},{"_id":"7e9ef870a03f12a0c472bd13","_tpl":"58dd3ad986f77403051cba8f","parentId":"5fe49444ae6628187a2e77ac","slotId":"main","location":{"x":2,"y":0,"r":"Horizontal","isSearched":true},"upd":{"StackObjectsCount":40}},{"_id":"ac15749e20d25c4ae3a53e3c","_tpl":"58dd3ad986f77403051cba8f","parentId":"5fe49444ae6628187a2e77ac","slotId":"main","location":{"x":0,"y":0,"r":"Horizontal","isSearched":true},"upd":{"StackObjectsCount":40}},{"_id":"6aa20d2574144e38f6a11dd7","_tpl":"5e4abc1f86f774069619fbaa","parentId":"5fe49444ae6628187a2e77b8","slotId":"TacticalVest","upd":{"StackObjectsCount":1}},{"_id":"fa98d7dd5e24d9f7559cfd12","_tpl":"5648a7494bdc2d9d488b4583","parentId":"5fe49444ae6628187a2e77b8","slotId":"ArmorVest","upd":{"StackObjectsCount":1}},{"_id":"bea725fe43e35552497ffa8f","_tpl":"5ac6ru7build5246662898107","parentId":"fa98d7dd5e24d9f7559cfd12","slotId":"mod_equipment_000"},{"_id":"b7ecb5b75b70e1548baead43","_tpl":"5c0d2727d174af02a012cf58","parentId":"5fe49444ae6628187a2e77b8","slotId":"Headwear","upd":{"StackObjectsCount":1,"Togglable":{"On":true}}},{"_id":"57a614432c7b001f3f5faacf","_tpl":"54491bb74bdc2d09088b4567","parentId":"5fe49444ae6628187a2e77b8","slotId":"Scabbard","upd":{"StackObjectsCount":1}},{"_id":"e16b1b5eb8477cf8024d6adf","_tpl":"5c501a4d2e221602b412b540","parentId":"5fe49444ae6628187a2e77b8","slotId":"FirstPrimaryWeapon","upd":{"Repairable":{"Durability":61,"MaxDurability":66}}},{"_id":"f191a2377e12efb14494857a","_tpl":"5c5039be2e221602b177c9ff","parentId":"e16b1b5eb8477cf8024d6adf","slotId":"mod_gas_block","upd":{"StackObjectsCount":1}},{"_id":"109f5eced56dd453aa497441","_tpl":"5c503d0a2e221602b542b7ef","parentId":"e16b1b5eb8477cf8024d6adf","slotId":"mod_reciever","upd":{"StackObjectsCount":1}},{"_id":"e123365e679aa8d726248a15","_tpl":"5a2a57cfc4a2826c6e06d44a","parentId":"6aa20d2574144e38f6a11dd7","slotId":"2","location":{"x":0,"y":0,"r":"Horizontal","isSearched":true},"upd":{"StackObjectsCount":1}},{"_id":"240e2878444e360bea69654e","_tpl":"5e9dcf5986f7746c417435b3","parentId":"5fe49444ae6628187a2e77b8","slotId":"Backpack","upd":{"StackObjectsCount":1}},{"_id":"0efa4293485c783049a3d3ef","_tpl":"58dd3ad986f77403051cba8f","parentId":"350283735b14b2c520c34050","slotId":"cartridges","location":0,"upd":{"StackObjectsCount":5}},{"_id":"3b109f90c805cc3810a8aca6","_tpl":"5c503ad32e2216398b5aada2","parentId":"6aa20d2574144e38f6a11dd7","slotId":"1","location":{"x":0,"y":0,"r":"Horizontal","isSearched":true},"upd":{"StackObjectsCount":1}},{"_id":"0552d4847f994a8e655b27c3","_tpl":"5c503ad32e2216398b5aada2","parentId":"e16b1b5eb8477cf8024d6adf","slotId":"mod_magazine","upd":{"StackObjectsCount":1}},{"_id":"2ca804d2aa9de51d80194e54","_tpl":"5c503ac82e221602b21d6e9a","parentId":"6aa20d2574144e38f6a11dd7","slotId":"1","location":{"x":0,"y":1,"r":"Horizontal","isSearched":true},"upd":{"StackObjectsCount":1}},{"_id":"350283735b14b2c520c34050","_tpl":"5c503ac82e221602b21d6e9a","parentId":"5fe49444ae6628187a2e77b6","slotId":"pocket1","location":{"x":0,"y":0,"r":"Horizontal","isSearched":true},"upd":{"StackObjectsCount":1}},{"_id":"c2863df5f151ec97846757b3","_tpl":"5f63405df5750b524b45f114","parentId":"e16b1b5eb8477cf8024d6adf","slotId":"mod_stock","upd":{"StackObjectsCount":1}},{"_id":"61bba4b6e522f28781a3654f","_tpl":"5649d9a14bdc2d79388b4580","parentId":"e16b1b5eb8477cf8024d6adf","slotId":"mod_sight_rear","upd":{"StackObjectsCount":1}},{"_id":"058cd8cbb0dcf585449817e1","_tpl":"57ae0171245977343c27bfcf","parentId":"61bba4b6e522f28781a3654f","slotId":"mod_scope","upd":{"StackObjectsCount":1}},{"_id":"f6d8b86f6335d84757004579","_tpl":"58dd3ad986f77403051cba8f","parentId":"3b109f90c805cc3810a8aca6","slotId":"cartridges","location":0,"upd":{"StackObjectsCount":10}},{"_id":"b90b857c23297eae3b0e0c3e","_tpl":"58dd3ad986f77403051cba8f","parentId":"0552d4847f994a8e655b27c3","slotId":"cartridges","location":0,"upd":{"StackObjectsCount":10}},{"_id":"1d2164c5a9d2a05841622f39","_tpl":"58dd3ad986f77403051cba8f","parentId":"2ca804d2aa9de51d80194e54","slotId":"cartridges","location":0,"upd":{"StackObjectsCount":5}},{"_id":"a664f9fe938def6e8cdc04ae","_tpl":"5f63407e1b231926f2329f15","parentId":"e16b1b5eb8477cf8024d6adf","slotId":"mod_muzzle","upd":{"StackObjectsCount":1}},{"_id":"b833077511c6d8398dfcab9d","_tpl":"5cdeac22d7f00c000f26168f","parentId":"240e2878444e360bea69654e","slotId":"main","location":{"x":0,"y":0,"r":"Horizontal","isSearched":true},"upd":{"StackObjectsCount":1}},{"_id":"88fd181a2b54a7fb792ccf72","_tpl":"5fc0f9b5d724d907e2077d82","parentId":"240e2878444e360bea69654e","slotId":"main","location":{"x":3,"y":0,"r":"Horizontal","isSearched":true},"upd":{"StackObjectsCount":1}}],"fastPanel":{}}