{"equipment":"5fe49444ae6628187a2e77b8","stash":"5fe49444ae6628187a2e78b8","questRaidItems":"5fe49444ae6628187a2e78b9","questStashItems":"5fe49444ae6628187a2e78ba","items":[{"_id":"5fe49444ae6628187a2e77b8","_tpl":"55d7217a4bdc2d86028b456d"},{"_id":"5fe49444ae6628187a2e77ac","_tpl":"5857a8bc2459772bad15db29","parentId":"5fe49444ae6628187a2e77b8","slotId":"SecuredContainer"},{"_id":"5fe49444ae6628187a2e77b6","_tpl":"557ffd194bdc2d28148b457f","parentId":"5fe49444ae6628187a2e77b8","slotId":"Pockets"},{"_id":"5fe49444ae6628187a2e78b8","_tpl":"5811ce772459770e9e5f9532"},{"_id":"5fe49444ae6628187a2e78ba","_tpl":"5963866b86f7747bfa1c4462"},{"_id":"5fe49444ae6628187a2e78b9","_tpl":"5963866286f7747bf429b572"},{"_id":"3293c67a1597bb12514c9a20","_tpl":"590c661e86f7741e566b646a","parentId":"5fe49444ae6628187a2e77ac","slotId":"main","location":{"x":1,"y":1,"r":"Vertical","isSearched":true},"upd":{"StackObjectsCount":1}},{"_id":"76d75ff32bc7a339c369e2de","_tpl":"5e8f3423fd7471236e6e3b64","parentId":"5fe49444ae6628187a2e77ac","slotId":"main","location":{"x":0,"y":1,"r":"Horizontal","isSearched":true},"upd":{"StackObjectsCount":1}},{"_id":"53b080d64e0b4092fbcc5311","_tpl":"5f647f31b6238e5dd066e196","parentId":"5fe49444ae6628187a2e77ac","slotId":"main","location":{"x":2,"y":0,"r":"Horizontal","isSearched":true},"upd":{"StackObjectsCount":15}},{"_id":"5125deaa571fd6f3ae2af410","_tpl":"5f647f31b6238e5dd066e196","parentId":"5fe49444ae6628187a2e77ac","slotId":"main","location":{"x":1,"y":0,"r":"Horizontal","isSearched":true},"upd":{"StackObjectsCount":15}},{"_id":"ffef41d5e1a319d646a9f172","_tpl":"5f647f31b6238e5dd066e196","parentId":"5fe49444ae6628187a2e77ac","slotId":"main","location":{"x":0,"y":0,"r":"Horizontal","isSearched":true},"upd":{"StackObjectsCount":15}},{"_id":"09fbdca05b195947c72e2ee2","_tpl":"59e7643b86f7742cbf2c109a","parentId":"5fe49444ae6628187a2e77b8","slotId":"TacticalVest","upd":{"StackObjectsCount":1}},{"_id":"9b3fafa0d74c1fc179886507","_tpl":"5df8a2ca86f7740bfe6df777","parentId":"5fe49444ae6628187a2e77b8","slotId":"ArmorVest","upd":{"StackObjectsCount":1}},{"_id":"7aff8ad45281e16a55fdae85","_tpl":"5ac6ru7build5246662898107","parentId":"9b3fafa0d74c1fc179886507","slotId":"mod_equipment_000"},{"_id":"279411f124f3030a52a5992c","_tpl":"5e848cc2988a8701445df1e8","parentId":"5fe49444ae6628187a2e77b8","slotId":"FirstPrimaryWeapon","upd":{"Repairable":{"Durability":61,"MaxDurability":66}}},{"_id":"b3f4f1fea0726d2d15615a7c","_tpl":"5e848d1c264f7c180b5e35a9","parentId":"279411f124f3030a52a5992c","slotId":"mod_barrel","upd":{"StackObjectsCount":1}},{"_id":"4f222454439842e98f130ede","_tpl":"5e848d51e4dbc5266a4ec63b","parentId":"279411f124f3030a52a5992c","slotId":"mod_handguard","upd":{"StackObjectsCount":1}},{"_id":"ec6bf23e60134a283a8cda65","_tpl":"5f647d9f8499b57dc40ddb93","parentId":"279411f124f3030a52a5992c","slotId":"mod_magazine","upd":{"StackObjectsCount":1}},{"_id":"00c4d4f0605543bf380170a0","_tpl":"5e848d99865c0f329958c83b","parentId":"279411f124f3030a52a5992c","slotId":"mod_stock","upd":{"StackObjectsCount":1}},{"_id":"685a6951aa50a7ea04f61d2b","_tpl":"5c06c6a80db834001b735491","parentId":"5fe49444ae6628187a2e77b8","slotId":"Headwear","upd":{"StackObjectsCount":1}},{"_id":"153306459cc6b3120b4fceed","_tpl":"5e85a9f4add9fe03027d9bf1","parentId":"279411f124f3030a52a5992c","slotId":"patron_in_weapon","upd":{"StackObjectsCount":1}},{"_id":"7ac9df649ce9a33ced4d6f06","_tpl":"5f647f31b6238e5dd066e196","parentId":"09fbdca05b195947c72e2ee2","slotId":"4","location":{"x":0,"y":0,"r":"Horizontal","isSearched":true},"upd":{"StackObjectsCount":4}},{"_id":"eabd488d3eacd20bfad1868c","_tpl":"5f647f31b6238e5dd066e196","parentId":"ec6bf23e60134a283a8cda65","slotId":"cartridges","location":0,"upd":{"StackObjectsCount":3}},{"_id":"09687e7690825c219fc674c4","_tpl":"5f647f31b6238e5dd066e196","parentId":"09fbdca05b195947c72e2ee2","slotId":"5","location":{"x":0,"y":0,"r":"Horizontal","isSearched":true},"upd":{"StackObjectsCount":5}}],"fastPanel":{}}